flask_fuzhu/__init__.py
flask_fuzhu/decorator.py
flask_fuzhu/exception.py
flask_fuzhu-0.0.6.dist-info/LICENSE
flask_fuzhu-0.0.6.dist-info/METADATA
flask_fuzhu-0.0.6.dist-info/WHEEL
flask_fuzhu-0.0.6.dist-info/top_level.txt
flask_fuzhu-0.0.6.dist-info/RECORD
