Metadata-Version: 2.1
Name: flask-fuzhu
Version: 0.0.6
Summary: practice build package
Home-page: UNKNOWN
Author: littlx
Author-email: littlx@qq.com
License: UNKNOWN
Platform: UNKNOWN
Requires-Python: >=3.9
License-File: LICENSE
Requires-Dist: flask
